palma/__init__.py
palma/automl/__init__.py
palma/automl/automl.py
palma/base/__init__.py
palma/base/engine.py
palma/base/model.py
palma/base/model_selection.py
palma/base/project.py
palma/base/splitting_strategy.py
palma/components/__init__.py
palma/components/base.py
palma/components/checker.py
palma/components/dashboard.py
palma/components/data_checker.py
palma/components/data_profiler.py
palma/components/logger.py
palma/components/performance.py
palma/components/shap.py
palma/datasets/__init__.py
palma/preprocessing/__init__.py
palma/preprocessing/na_encoder.py
palma/preprocessing/pca.py
palma/utils/__init__.py
palma/utils/checker.py
palma/utils/names.py
palma/utils/plotting.py
palma/utils/utils.py
palma-2025.1.5.dist-info/licenses/LICENSE
palma-2025.1.5.dist-info/METADATA
palma-2025.1.5.dist-info/WHEEL
palma-2025.1.5.dist-info/top_level.txt
palma-2025.1.5.dist-info/RECORD
