Metadata-Version: 2.4
Name: palma
Version: 2025.1.5
Author-email: Vincent Laurent <vincent.laurent@mews-labs.com>
Requires-Python: >=3.9
License-File: LICENSE
Requires-Dist: seaborn>0.12.0
Requires-Dist: tabulate>0.8.10
Requires-Dist: frozendict>2.3.4
Requires-Dist: flaml[automl]>=2
Requires-Dist: matplotlib>=3.4
Requires-Dist: numpy>=1
Requires-Dist: scikit-learn>1.5
Requires-Dist: pandas>=1
Requires-Dist: shap
Requires-Dist: llvmlite>=0.39
Requires-Dist: xgboost>2
Requires-Dist: pyaml>12
Requires-Dist: llvmlite
Requires-Dist: numba
Provides-Extra: components
Requires-Dist: deepchecks; extra == "components"
Requires-Dist: ydata-profiling; extra == "components"
Requires-Dist: plot-metric; extra == "components"
Requires-Dist: mlflow; extra == "components"
Requires-Dist: boto3; extra == "components"
Requires-Dist: explainerdashboard; extra == "components"
Requires-Dist: anywidget; extra == "components"
Provides-Extra: test
Requires-Dist: pylint; extra == "test"
Requires-Dist: coverage; extra == "test"
Requires-Dist: pytest; extra == "test"
Requires-Dist: pytest-cov; extra == "test"
Requires-Dist: jupyter; extra == "test"
Requires-Dist: notebook; extra == "test"
Requires-Dist: uci_dataset; extra == "test"
Provides-Extra: doc
Requires-Dist: sphinx; extra == "doc"
Requires-Dist: sphinx-book-theme; extra == "doc"
Requires-Dist: myst-parser; extra == "doc"
Requires-Dist: sphinx-copybutton; extra == "doc"
Requires-Dist: sphinx-favicon; extra == "doc"
Requires-Dist: nbsphinx; extra == "doc"
Requires-Dist: sphinx-autoapi; extra == "doc"
Requires-Dist: sphinx-version-warning; extra == "doc"
Requires-Dist: sphinx-prompt; extra == "doc"
Requires-Dist: numpydoc; extra == "doc"
Dynamic: license-file
